odoo/addons/stock_picking_group_by_partner_by_carrier_by_date/README.rst
odoo/addons/stock_picking_group_by_partner_by_carrier_by_date/__init__.py
odoo/addons/stock_picking_group_by_partner_by_carrier_by_date/__manifest__.py
odoo/addons/stock_picking_group_by_partner_by_carrier_by_date/i18n/fr.po
odoo/addons/stock_picking_group_by_partner_by_carrier_by_date/i18n/it.po
odoo/addons/stock_picking_group_by_partner_by_carrier_by_date/i18n/pt_BR.po
odoo/addons/stock_picking_group_by_partner_by_carrier_by_date/i18n/stock_picking_group_by_partner_by_carrier_by_date.pot
odoo/addons/stock_picking_group_by_partner_by_carrier_by_date/models/__init__.py
odoo/addons/stock_picking_group_by_partner_by_carrier_by_date/models/stock_move.py
odoo/addons/stock_picking_group_by_partner_by_carrier_by_date/models/stock_picking_type.py
odoo/addons/stock_picking_group_by_partner_by_carrier_by_date/readme/CONTRIBUTORS.md
odoo/addons/stock_picking_group_by_partner_by_carrier_by_date/readme/CREDITS.md
odoo/addons/stock_picking_group_by_partner_by_carrier_by_date/readme/DESCRIPTION.md
odoo/addons/stock_picking_group_by_partner_by_carrier_by_date/readme/USAGE.md
odoo/addons/stock_picking_group_by_partner_by_carrier_by_date/static/description/icon.png
odoo/addons/stock_picking_group_by_partner_by_carrier_by_date/static/description/index.html
odoo/addons/stock_picking_group_by_partner_by_carrier_by_date/tests/__init__.py
odoo/addons/stock_picking_group_by_partner_by_carrier_by_date/tests/test_grouping_by_date.py
odoo/addons/stock_picking_group_by_partner_by_carrier_by_date/views/stock_picking_type.xml
odoo_addon_stock_picking_group_by_partner_by_carrier_by_date-18.0.1.1.0.dist-info/METADATA
odoo_addon_stock_picking_group_by_partner_by_carrier_by_date-18.0.1.1.0.dist-info/WHEEL
odoo_addon_stock_picking_group_by_partner_by_carrier_by_date-18.0.1.1.0.dist-info/top_level.txt
odoo_addon_stock_picking_group_by_partner_by_carrier_by_date-18.0.1.1.0.dist-info/RECORD
