Metadata-Version: 2.1
Name: odoo-addon-stock_picking_group_by_partner_by_carrier_by_date
Version: 18.0.1.1.0
Requires-Python: >=3.10
Requires-Dist: odoo-addon-partner_tz==18.0.*
Requires-Dist: odoo-addon-stock_picking_group_by_partner_by_carrier==18.0.*
Requires-Dist: odoo==18.0.*
Summary: Stock Picking: group by partner and carrier and scheduled date
Home-page: https://github.com/OCA/stock-logistics-workflow
License: AGPL-3
Author: Camptocamp, Odoo Community Association (OCA)
Author-email: support@odoo-community.org
Classifier: Programming Language :: Python
Classifier: Framework :: Odoo
Classifier: Framework :: Odoo :: 18.0
Classifier: License :: OSI Approved :: GNU Affero General Public License v3
Classifier: Development Status :: 3 - Alpha
